fpbinary.cp35-win_amd64.pyd
fpbinary-1.5.8.dist-info/LICENSE
fpbinary-1.5.8.dist-info/METADATA
fpbinary-1.5.8.dist-info/WHEEL
fpbinary-1.5.8.dist-info/top_level.txt
fpbinary-1.5.8.dist-info/RECORD
