Metadata-Version: 2.1
Name: fpbinary
Version: 1.5.8
Summary: Provides binary fixed point functionality.
Home-page: https://github.com/smlgit/fpbinary
Author-email: smlgit@protonmail.com
License: GPL-2.0 License
Project-URL: Documentation, https://fpbinary.readthedocs.io/en/latest/
Project-URL: Source, https://github.com/smlgit/fpbinary
Keywords: fixed-point,binary,bit-accurate,dsp,fpga
Platform: UNKNOWN
Classifier: Operating System :: Microsoft :: Windows
Classifier: Operating System :: POSIX
Classifier: Operating System :: MacOS :: MacOS X
Classifier: Programming Language :: Python :: 2.7
Classifier: Programming Language :: Python :: 3
Requires-Python: >=2.7
